func_adl_servicex_xaodr25/__init__.py
func_adl_servicex_xaodr25/_rb_tree_node_base.py
func_adl_servicex_xaodr25/calibration_event_config.py
func_adl_servicex_xaodr25/calibration_support.py
func_adl_servicex_xaodr25/calosampling.py
func_adl_servicex_xaodr25/condition_variable.py
func_adl_servicex_xaodr25/default_calibration_config.py
func_adl_servicex_xaodr25/elementlink_datavector_xaod_afpproton_v1__.py
func_adl_servicex_xaodr25/elementlink_datavector_xaod_afpsihit_v2__.py
func_adl_servicex_xaodr25/elementlink_datavector_xaod_afpsihitscluster_v1__.py
func_adl_servicex_xaodr25/elementlink_datavector_xaod_afptofhit_v1__.py
func_adl_servicex_xaodr25/elementlink_datavector_xaod_afptoftrack_v1__.py
func_adl_servicex_xaodr25/elementlink_datavector_xaod_afptrack_v2__.py
func_adl_servicex_xaodr25/elementlink_datavector_xaod_calocluster_v1__.py
func_adl_servicex_xaodr25/elementlink_datavector_xaod_eventinfo_v1__.py
func_adl_servicex_xaodr25/elementlink_datavector_xaod_iparticle__.py
func_adl_servicex_xaodr25/elementlink_datavector_xaod_jet_v1__.py
func_adl_servicex_xaodr25/elementlink_datavector_xaod_jgtower_v1__.py
func_adl_servicex_xaodr25/elementlink_datavector_xaod_l2standalonemuon_v2__.py
func_adl_servicex_xaodr25/elementlink_datavector_xaod_muon_v1__.py
func_adl_servicex_xaodr25/elementlink_datavector_xaod_muonsegment_v1__.py
func_adl_servicex_xaodr25/elementlink_datavector_xaod_neutralparticle_v1__.py
func_adl_servicex_xaodr25/elementlink_datavector_xaod_pfo_v1__.py
func_adl_servicex_xaodr25/elementlink_datavector_xaod_ringset_v1__.py
func_adl_servicex_xaodr25/elementlink_datavector_xaod_tautrack_v1__.py
func_adl_servicex_xaodr25/elementlink_datavector_xaod_trackmeasurementvalidation_v1__.py
func_adl_servicex_xaodr25/elementlink_datavector_xaod_trackparticle_v1__.py
func_adl_servicex_xaodr25/elementlink_datavector_xaod_trigbphys_v1__.py
func_adl_servicex_xaodr25/elementlink_datavector_xaod_trigemcluster_v1__.py
func_adl_servicex_xaodr25-2.4.5.25.2.41.dist-info/METADATA
func_adl_servicex_xaodr25-2.4.5.25.2.41.dist-info/WHEEL
func_adl_servicex_xaodr25-2.4.5.25.2.41.dist-info/RECORD
